hamerspace/__init__.py
hamerspace/cli.py
hamerspace/backends/__init__.py
hamerspace/backends/base.py
hamerspace/backends/loader.py
hamerspace/backends/onnx_backend.py
hamerspace/backends/openvino_backend.py
hamerspace/backends/pytorch_backend.py
hamerspace/benchmarks/__init__.py
hamerspace/benchmarks/benchmarker.py
hamerspace/core/__init__.py
hamerspace/core/backends.py
hamerspace/core/constraints.py
hamerspace/core/goals.py
hamerspace/core/models.py
hamerspace/core/optimizer.py
hamerspace/core/result.py
hamerspace/strategies/__init__.py
hamerspace/strategies/strategy.py
hamerspace/strategies/strategy_selector.py
hamerspace/utils/__init__.py
hamerspace/utils/logger.py
hamerspace-0.1.0.dist-info/licenses/LICENSE
hamerspace-0.1.0.dist-info/METADATA
hamerspace-0.1.0.dist-info/WHEEL
hamerspace-0.1.0.dist-info/top_level.txt
hamerspace-0.1.0.dist-info/RECORD
