Metadata-Version: 2.4
Name: hamerspace
Version: 0.1.0
Summary: Model compression and optimization engine for non-LLM machine learning models
Home-page: https://github.com/yourusername/hamerspace
Author: Hamerspace Contributors
Author-email: 
License: Apache-2.0
Project-URL: Homepage, https://github.com/yourusername/hamerspace
Project-URL: Documentation, https://hamerspace.readthedocs.io
Project-URL: Repository, https://github.com/yourusername/hamerspace
Project-URL: Bug Tracker, https://github.com/yourusername/hamerspace/issues
Keywords: machine-learning,model-compression,quantization,pruning,optimization,deep-learning,pytorch,tensorflow,onnx
Classifier: Development Status :: 3 - Alpha
Classifier: Intended Audience :: Developers
Classifier: Intended Audience :: Science/Research
Classifier: Topic :: Scientific/Engineering :: Artificial Intelligence
Classifier: License :: OSI Approved :: Apache Software License
Classifier: Programming Language :: Python :: 3
Classifier: Programming Language :: Python :: 3.8
Classifier: Programming Language :: Python :: 3.9
Classifier: Programming Language :: Python :: 3.10
Classifier: Programming Language :: Python :: 3.11
Requires-Python: >=3.8
License-File: LICENSE
Requires-Dist: torch>=2.0.0
Requires-Dist: tensorflow>=2.13.0
Requires-Dist: onnx>=1.14.0
Requires-Dist: onnxruntime>=1.15.0
Requires-Dist: transformers>=4.30.0
Requires-Dist: optimum>=1.12.0
Requires-Dist: numpy>=1.24.0
Requires-Dist: pandas>=2.0.0
Requires-Dist: pydantic>=2.0.0
Requires-Dist: tqdm>=4.65.0
Requires-Dist: psutil>=5.9.0
Provides-Extra: full
Requires-Dist: openvino>=2023.0.0; extra == "full"
Requires-Dist: bitsandbytes>=0.41.0; extra == "full"
Requires-Dist: apache-tvm>=0.12.0; extra == "full"
Provides-Extra: dev
Requires-Dist: pytest>=7.3.0; extra == "dev"
Requires-Dist: pytest-cov>=4.1.0; extra == "dev"
Requires-Dist: black>=23.3.0; extra == "dev"
Requires-Dist: isort>=5.12.0; extra == "dev"
Requires-Dist: flake8>=6.0.0; extra == "dev"
Requires-Dist: mypy>=1.3.0; extra == "dev"
Dynamic: home-page
Dynamic: license-file
Dynamic: requires-python
